LICENSE.AGPL.txt
LICENSE.txt
MANIFEST.in
README.md
pyproject.toml
setup.cfg
setup.py
django_powertables.egg-info/PKG-INFO
django_powertables.egg-info/SOURCES.txt
django_powertables.egg-info/dependency_links.txt
django_powertables.egg-info/requires.txt
django_powertables.egg-info/top_level.txt
docs/.gitkeep
powertables/__init__.py
powertables/apps.py
powertables/models.py
powertables/utils.py
powertables/views.py
powertables/__pycache__/__init__.cpython-38.pyc
powertables/__pycache__/apps.cpython-38.pyc
powertables/__pycache__/models.cpython-38.pyc
powertables/__pycache__/utils.cpython-38.pyc
powertables/__pycache__/views.cpython-38.pyc
powertables/templates/powertables/_arrows.html
powertables/templates/powertables/powertable.html
powertables/templatetags/__init__.py
powertables/templatetags/powertable_tags.py
powertables/templatetags/__pycache__/__init__.cpython-38.pyc
powertables/templatetags/__pycache__/powertable_tags.cpython-38.pyc