Metadata-Version: 2.1
Name: django-powertables
Version: 0.2.0
Summary: A sortable filter table implementation for the Django web framework.
Home-page: https://github.com/destacks/powertables
Author: Alexis Michaltsis
Author-email: info@destacks.com
License: AGPLv3+ and commercial license available
Platform: UNKNOWN
Classifier: Environment :: Web Environment
Classifier: Framework :: Django
Classifier: Framework :: Django :: 3.2
Classifier: Intended Audience :: Developers
Classifier: Operating System :: OS Independent
Classifier: Programming Language :: Python
Classifier: Programming Language :: Python :: 3
Classifier: Programming Language :: Python :: 3 :: Only
Classifier: Programming Language :: Python :: 3.8
Classifier: Topic :: Internet :: WWW/HTTP
Classifier: Topic :: Internet :: WWW/HTTP :: Dynamic Content
